c2xg/Association.py
c2xg/Candidates.py
c2xg/Loader.py
c2xg/MDL.py
c2xg/Parser.py
c2xg/Word_Classes.py
c2xg/__init__.py
c2xg/c2xg.py
c2xg-2.2.dist-info/LICENSE.txt
c2xg-2.2.dist-info/METADATA
c2xg-2.2.dist-info/WHEEL
c2xg-2.2.dist-info/top_level.txt
c2xg-2.2.dist-info/RECORD
