Metadata-Version: 2.1
Name: c2xg
Version: 2.2
Summary: Construction Grammars for Natural Language Processing and Computational Linguistics
Home-page: http://www.c2xg.io
Author: Jonathan Dunn
Author-email: jedunn@illinois.edu
License: LGPL 3.0
Keywords: grammar induction,syntax,cxg,unsupervised learning,natural language processing,computational linguistics,construction grammar,cognitive linguistics,usage-based grammar
Requires-Python: >=3.7
License-File: LICENSE.txt
Requires-Dist: clean-text >=0.6.0
Requires-Dist: cytoolz >=0.12.2
Requires-Dist: gensim >=4.0.1
Requires-Dist: kmedoids >=0.3.3
Requires-Dist: matplotlib >=3.5.3
Requires-Dist: numpy >=1.21.6
Requires-Dist: pandas >=1.3.5
Requires-Dist: scipy >=1.7.3
Requires-Dist: scikit-learn >=1.0.2
Requires-Dist: statsmodels >=0.13.5
